Workbook
Name scen: Supuestos!$B$2
Name iva: Supuestos!$B$3
Name pay_pct: Supuestos!$B$4
Name pay_fix: Supuestos!$B$5
Name ship: Supuestos!$B$6
Name pack: Supuestos!$B$7
Name ship_charge: Supuestos!$B$8
Name free_from: Supuestos!$B$9
Name ret: Supuestos!$B$10
Name c_nose: Supuestos!$B$11
Name c_spot: Supuestos!$B$12
Name r_nose: Supuestos!$B$13
Name r_spot: Supuestos!$B$14
Name land: Supuestos!$B$15
Name fixed: Supuestos!$B$16
Name spend0: Supuestos!$B$17
Name cash0: Supuestos!$B$18
Name st_n0: Supuestos!$B$19
Name st_s0: Supuestos!$B$20
Name aport: Supuestos!$B$21
Name aport_lim: Supuestos!$B$22
Name reinv: Supuestos!$B$23
Name cap1: Supuestos!$B$24
Name cap2: Supuestos!$B$25
Name cpm1: Supuestos!$B$26
Name cpm2: Supuestos!$B$27
Name cpm3: Supuestos!$B$28
Name ctr1: Supuestos!$B$29
Name ctr2: Supuestos!$B$30
Name ctr3: Supuestos!$B$31
Name rep1: Supuestos!$B$32
Name rep2: Supuestos!$B$33
Name rep3: Supuestos!$B$34
Name lead1: Supuestos!$B$35
Name lead2: Supuestos!$B$36
Name lead3: Supuestos!$B$37
Name lcv1: Supuestos!$B$38
Name lcv2: Supuestos!$B$39
Name lcv3: Supuestos!$B$40
Name aov: Supuestos!$G$63
Name net_avg: Supuestos!$H$63
Name pay_avg: Supuestos!$I$63
Name nose_per: Supuestos!$D$63
Name spot_per: Supuestos!$E$63
Name contrib_avg: Supuestos!$J$63

Sheet Supuestos
A1: Parámetro | B1: Valor | C1: Nombre
A2: Escenario (1=Pesimista, 2=Base, 3=Optimista) | B2: 2 | C2: scen
A3: IVA | B3: 0.21 | C3: iva
A4: Stripe % | B4: 0.015 | C4: pay_pct
A5: Stripe fijo € | B5: 0.25 | C5: pay_fix
A6: Etiqueta envío neto € | B6: 3.2231405 | C6: ship
A7: Sobre neto € | B7: 0.2892562 | C7: pack
A8: Envío cobrado al cliente € | B8: 3.9 | C8: ship_charge
A9: Envío gratis desde € | B9: 30 | C9: free_from
A10: Devoluciones % | B10: 0.02 | C10: ret
A11: Coste nariz piloto neto € | B11: 2.9 | C11: c_nose
A12: Coste granos piloto neto € | B12: 1.6 | C12: c_spot
A13: Coste nariz reposición neto € | B13: 2.07 | C13: r_nose
... A40: Conversión leads optimista | B40: 0.04 | C40: lcv3
A42: Mes | B42: CVR pesimista | C42: CVR base | D42: CVR optimista
A43: 0 | B43: 0.012 | C43: 0.018 | D43: 0.022
A44: 1 | B44: 0.014 | C44: 0.022 | D44: 0.028
A45: 2 | B45: 0.016 | C45: 0.026 | D45: 0.034
A46: 3 | B46: 0.018 | C46: 0.03 | D46: 0.04
A47: 4 | B47: 0.02 | C47: 0.032 | D47: 0.044
A48: 5 | B48: 0.02 | C48: 0.033 | D48: 0.045
A49: 6 | B49: 0.02 | C49: 0.033 | D49: 0.045
A50: 7 | B50: 0.02 | C50: 0.033 | D50: 0.045
A51: 8 | B51: 0.02 | C51: 0.033 | D51: 0.045
A52: 9 | B52: 0.02 | C52: 0.033 | D52: 0.045
A53: 10 | B53: 0.02 | C53: 0.033 | D53: 0.045
A54: 11 | B54: 0.02 | C54: 0.033 | D54: 0.045
A55: 12 | B55: 0.02 | C55: 0.033 | D55: 0.045
A57: Oferta | B57: Precio | C57: Coste producto | D57: Cajas nariz | E57: Cajas granos | F57: Mix | G57: Cobrado | H57: Neto | I57: Stripe | J57: Contribución
A58: 1 caja Nariz + envío 3,90 € | B58: 16.95 | C58: 2.9 | D58: 1 | E58: 0 | F58: 0.2 | G58: =B58+IF(B58<free_from,ship_charge,0) | H58: =G58/(1+iva) | I58: =G58*pay_pct+pay_fix | J58: =H58-C58-I58-ship-pack-H58*ret
A59: Dúo Noche (Nariz + Granos) | B59: 26.9 | C59: 4.5 | D59: 1 | E59: 1 | F59: 0.2 | G59: =B59+IF(B59<free_from,ship_charge,0) | H59: =G59/(1+iva) | I59: =G59*pay_pct+pay_fix | J59: =H59-C59-I59-ship-pack-H59*ret
A60: 2 cajas Nariz | B60: 29.9 | C60: 5.8 | D60: 2 | E60: 0 | F60: 0.45 | G60: =B60+IF(B60<free_from,ship_charge,0) | H60: =G60/(1+iva) | I60: =G60*pay_pct+pay_fix | J60: =H60-C60-I60-ship-pack-H60*ret
A61: 3 cajas Nariz | B61: 39.9 | C61: 8.7 | D61: 3 | E61: 0 | F61: 0.1 | G61: =B61+IF(B61<free_from,ship_charge,0) | H61: =G61/(1+iva) | I61: =G61*pay_pct+pay_fix | J61: =H61-C61-I61-ship-pack-H61*ret
A62: Mes completo (2 Nariz + 1 Granos) | B62: 42.9 | C62: 7.4 | D62: 2 | E62: 1 | F62: 0.05 | G62: =B62+IF(B62<free_from,ship_charge,0) | H62: =G62/(1+iva) | I62: =G62*pay_pct+pay_fix | J62: =H62-C62-I62-ship-pack-H62*ret
A63: Pedido medio | C63: =SUMPRODUCT(C58:C62,F58:F62) | D63: =SUMPRODUCT(D58:D62,F58:F62) | E63: =SUMPRODUCT(E58:E62,F58:F62) | F63: =SUM(F58:F62) | G63: =SUMPRODUCT(G58:G62,F58:F62) | H63: =SUMPRODUCT(H58:H62,F58:F62) | I63: =SUMPRODUCT(I58:I62,F58:F62) | J63: =SUMPRODUCT(J58:J62,F58:F62)

Sheet Modelo
A1: Mes | B1: Anuncios | C1: CPM | D1: CTR | E1: CPC | F1: Impresiones | G1: Clics | H1: Visitas | I1: CVR | J1: Pedidos pagados | K1: Recompra | L1: Pedidos email | M1: Pedidos | N1: Necesidad nariz | O1: Necesidad granos | P1: Reposición nariz (cajas) | Q1: Reposición granos (cajas) | R1: Coste reposición | S1: Stock nariz tras repo | T1: Valor nariz tras repo | U1: Coste unit. nariz | V1: Stock granos tras repo | W1: Valor granos tras repo | X1: Coste unit. granos | Y1: Stock nariz fin | Z1: Valor nariz fin | AA1: Stock granos fin | AB1: Valor granos fin | AC1: Cobrado | AD1: Neto | AE1: IVA repercutido | AF1: Producto | AG1: Stripe | AH1: Envío+sobre | AI1: Devoluciones | AJ1: Contribución | AK1: Fijos | AL1: Resultado | AM1: CPA | AN1: ROAS | AO1: IVA soportado | AP1: IVA trimestre | AQ1: Aportación | AR1: Caja fin
A2: 0 | B2: =spend0 | C2: =CHOOSE(scen,cpm1,cpm2,cpm3) | D2: =CHOOSE(scen,ctr1,ctr2,ctr3) | E2: =C2/1000/D2 | F2: =B2/C2*1000 | G2: =F2*D2 | H2: =G2*land | I2: =CHOOSE(scen,Supuestos!B43,Supuestos!C43,Supuestos!D43) | J2: =H2*I2 | K2: 0 | L2: =H2*CHOOSE(scen,lead1,lead2,lead3)*CHOOSE(scen,lcv1,lcv2,lcv3) | M2: =J2+K2+L2 | N2: =M2*nose_per | O2: =M2*spot_per | P2: =IF(st_n0-N2<60,MAX(125,CEILING(N2*2.5/125,1)*125),0) | Q2: =IF(st_s0-O2<20,MAX(60,CEILING(O2*2.5*1.5,1))/1.5,0) | R2: =P2*r_nose+Q2*r_spot | S2: =st_n0+P2 | T2: =st_n0*c_nose+P2*r_nose | U2: =IF(S2>0,T2/S2,c_nose) | V2: =st_s0+Q2 | W2: =st_s0*c_spot+Q2*r_spot | X2: =IF(V2>0,W2/V2,c_spot) | Y2: =S2-N2 | Z2: =T2-N2*U2 | AA2: =V2-O2 | AB2: =W2-O2*X2 | AC2: =M2*aov | AD2: =M2*net_avg | AE2: =AC2-AD2 | AF2: =N2*U2+O2*X2 | AG2: =M2*pay_avg | AH2: =M2*(ship+pack) | AI2: =AD2*ret | AJ2: =AD2-AF2-AG2-AH2-AI2 | AK2: =fixed | AL2: =AJ2-B2-AK2 | AM2: =IF(J2>0,B2/J2,0) | AN2: =IF(B2>0,J2*aov/B2,0) | AO2: =R2*iva+AH2*iva | AP2: 0 | AQ2: 0 | AR2: =cash0+AQ2+AC2-AG2-B2-AK2-R2*(1+iva)-AH2*(1+iva)-AP2-AI2
A3: 1 | B3: =IF(FALSE(),0,MIN(cap1,MAX(B2,reinv*AJ2+AQ3),MAX(0,AR2+AQ3))) | C3: =CHOOSE(scen,cpm1,cpm2,cpm3) | D3: =CHOOSE(scen,ctr1,ctr2,ctr3) | E3: =C3/1000/D3 | F3: =B3/C3*1000 | G3: =F3*D3 | H3: =G3*land | I3: =CHOOSE(scen,Supuestos!B44,Supuestos!C44,Supuestos!D44) | J3: =H3*I3 | K3: 0 | L3: =H3*CHOOSE(scen,lead1,lead2,lead3)*CHOOSE(scen,lcv1,lcv2,lcv3) | M3: =J3+K3+L3 | N3: =M3*nose_per | O3: =M3*spot_per | P3: =IF(Y2-N3<60,MAX(125,CEILING(N3*2.5/125,1)*125),0) | Q3: =IF(AA2-O3<20,MAX(60,CEILING(O3*2.5*1.5,1))/1.5,0) | R3: =P3*r_nose+Q3*r_spot | S3: =Y2+P3 | T3: =Z2+P3*r_nose | U3: =IF(S3>0,T3/S3,c_nose) | V3: =AA2+Q3 | W3: =AB2+Q3*r_spot | X3: =IF(V3>0,W3/V3,c_spot) | Y3: =S3-N3 | Z3: =T3-N3*U3 | AA3: =V3-O3 | AB3: =W3-O3*X3 | AC3: =M3*aov | AD3: =M3*net_avg | AE3: =AC3-AD3 | AF3: =N3*U3+O3*X3 | AG3: =M3*pay_avg | AH3: =M3*(ship+pack) | AI3: =AD3*ret | AJ3: =AD3-AF3-AG3-AH3-AI3 | AK3: =fixed | AL3: =AJ3-B3-AK3 | AM3: =IF(J3>0,B3/J3,0) | AN3: =IF(B3>0,J3*aov/B3,0) | AO3: =R3*iva+AH3*iva | AP3: 0 | AQ3: =IF(FALSE(),0,IF(AL2<aport_lim,aport,0)) | AR3: =AR2+AQ3+AC3-AG3-B3-AK3-R3*(1+iva)-AH3*(1+iva)-AP3-AI3
A4: 2 | B4: =IF(FALSE(),0,MIN(cap1,MAX(B3,reinv*AJ3+AQ4),MAX(0,AR3+AQ4))) | C4: =CHOOSE(scen,cpm1,cpm2,cpm3) | D4: =CHOOSE(scen,ctr1,ctr2,ctr3) | E4: =C4/1000/D4 | F4: =B4/C4*1000 | G4: =F4*D4 | H4: =G4*land | I4: =CHOOSE(scen,Supuestos!B45,Supuestos!C45,Supuestos!D45) | J4: =H4*I4 | K4: =CHOOSE(scen,rep1,rep2,rep3)*J2 | L4: =H4*CHOOSE(scen,lead1,lead2,lead3)*CHOOSE(scen,lcv1,lcv2,lcv3) | M4: =J4+K4+L4 | N4: =M4*nose_per | O4: =M4*spot_per | P4: =IF(Y3-N4<60,MAX(125,CEILING(N4*2.5/125,1)*125),0) | Q4: =IF(AA3-O4<20,MAX(60,CEILING(O4*2.5*1.5,1))/1.5,0) | R4: =P4*r_nose+Q4*r_spot | S4: =Y3+P4 | T4: =Z3+P4*r_nose | U4: =IF(S4>0,T4/S4,c_nose) | V4: =AA3+Q4 | W4: =AB3+Q4*r_spot | X4: =IF(V4>0,W4/V4,c_spot) | Y4: =S4-N4 | Z4: =T4-N4*U4 | AA4: =V4-O4 | AB4: =W4-O4*X4 | AC4: =M4*aov | AD4: =M4*net_avg | AE4: =AC4-AD4 | AF4: =N4*U4+O4*X4 | AG4: =M4*pay_avg | AH4: =M4*(ship+pack) | AI4: =AD4*ret | AJ4: =AD4-AF4-AG4-AH4-AI4 | AK4: =fixed | AL4: =AJ4-B4-AK4 | AM4: =IF(J4>0,B4/J4,0) | AN4: =IF(B4>0,J4*aov/B4,0) | AO4: =R4*iva+AH4*iva | AP4: 0 | AQ4: =IF(FALSE(),0,IF(AL3<aport_lim,aport,0)) | AR4: =AR3+AQ4+AC4-AG4-B4-AK4-R4*(1+iva)-AH4*(1+iva)-AP4-AI4
A5: 3 | B5: =IF(FALSE(),0,MIN(cap1,MAX(B4,reinv*AJ4+AQ5),MAX(0,AR4+AQ5))) | C5: =CHOOSE(scen,cpm1,cpm2,cpm3) | D5: =CHOOSE(scen,ctr1,ctr2,ctr3) | E5: =C5/1000/D5 | F5: =B5/C5*1000 | G5: =F5*D5 | H5: =G5*land | I5: =CHOOSE(scen,Supuestos!B46,Supuestos!C46,Supuestos!D46) | J5: =H5*I5 | K5: =CHOOSE(scen,rep1,rep2,rep3)*J3 | L5: =H5*CHOOSE(scen,lead1,lead2,lead3)*CHOOSE(scen,lcv1,lcv2,lcv3) | M5: =J5+K5+L5 | N5: =M5*nose_per | O5: =M5*spot_per | P5: =IF(Y4-N5<60,MAX(125,CEILING(N5*2.5/125,1)*125),0) | Q5: =IF(AA4-O5<20,MAX(60,CEILING(O5*2.5*1.5,1))/1.5,0) | R5: =P5*r_nose+Q5*r_spot | S5: =Y4+P5 | T5: =Z4+P5*r_nose | U5: =IF(S5>0,T5/S5,c_nose) | V5: =AA4+Q5 | W5: =AB4+Q5*r_spot | X5: =IF(V5>0,W5/V5,c_spot) | Y5: =S5-N5 | Z5: =T5-N5*U5 | AA5: =V5-O5 | AB5: =W5-O5*X5 | AC5: =M5*aov | AD5: =M5*net_avg | AE5: =AC5-AD5 | AF5: =N5*U5+O5*X5 | AG5: =M5*pay_avg | AH5: =M5*(ship+pack) | AI5: =AD5*ret | AJ5: =AD5-AF5-AG5-AH5-AI5 | AK5: =fixed | AL5: =AJ5-B5-AK5 | AM5: =IF(J5>0,B5/J5,0) | AN5: =IF(B5>0,J5*aov/B5,0) | AO5: =R5*iva+AH5*iva | AP5: =IF(AND(A5>0,MOD(A5,3)=0),SUM(AE2:AE4)-SUM(AO2:AO4),0) | AQ5: =IF(FALSE(),0,IF(AL4<aport_lim,aport,0)) | AR5: =AR4+AQ5+AC5-AG5-B5-AK5-R5*(1+iva)-AH5*(1+iva)-AP5-AI5
A6: 4 | B6: =IF((AM5>contrib_avg),0,MIN(cap1,MAX(B5,reinv*AJ5+AQ6),MAX(0,AR5+AQ6))) | C6: =CHOOSE(scen,cpm1,cpm2,cpm3) | D6: =CHOOSE(scen,ctr1,ctr2,ctr3) | E6: =C6/1000/D6 | F6: =B6/C6*1000 | G6: =F6*D6 | H6: =G6*land | I6: =CHOOSE(scen,Supuestos!B47,Supuestos!C47,Supuestos!D47) | J6: =H6*I6 | K6: =CHOOSE(scen,rep1,rep2,rep3)*J4 | L6: =H6*CHOOSE(scen,lead1,lead2,lead3)*CHOOSE(scen,lcv1,lcv2,lcv3) | M6: =J6+K6+L6 | N6: =M6*nose_per | O6: =M6*spot_per | P6: =IF(Y5-N6<60,MAX(125,CEILING(N6*2.5/125,1)*125),0) | Q6: =IF(AA5-O6<20,MAX(60,CEILING(O6*2.5*1.5,1))/1.5,0) | R6: =P6*r_nose+Q6*r_spot | S6: =Y5+P6 | T6: =Z5+P6*r_nose | U6: =IF(S6>0,T6/S6,c_nose) | V6: =AA5+Q6 | W6: =AB5+Q6*r_spot | X6: =IF(V6>0,W6/V6,c_spot) | Y6: =S6-N6 | Z6: =T6-N6*U6 | AA6: =V6-O6 | AB6: =W6-O6*X6 | AC6: =M6*aov | AD6: =M6*net_avg | AE6: =AC6-AD6 | AF6: =N6*U6+O6*X6 | AG6: =M6*pay_avg | AH6: =M6*(ship+pack) | AI6: =AD6*ret | AJ6: =AD6-AF6-AG6-AH6-AI6 | AK6: =fixed | AL6: =AJ6-B6-AK6 | AM6: =IF(J6>0,B6/J6,0) | AN6: =IF(B6>0,J6*aov/B6,0) | AO6: =R6*iva+AH6*iva | AP6: =IF(AND(A6>0,MOD(A6,3)=0),SUM(AE3:AE5)-SUM(AO3:AO5),0) | AQ6: =IF((AM5>contrib_avg),0,IF(AL5<aport_lim,aport,0)) | AR6: =AR5+AQ6+AC6-AG6-B6-AK6-R6*(1+iva)-AH6*(1+iva)-AP6-AI6
A7: 5 | B7: =IF((AM5>contrib_avg),0,MIN(cap1,MAX(B6,reinv*AJ6+AQ7),MAX(0,AR6+AQ7))) | C7: =CHOOSE(scen,cpm1,cpm2,cpm3) | D7: =CHOOSE(scen,ctr1,ctr2,ctr3) | E7: =C7/1000/D7 | F7: =B7/C7*1000 | G7: =F7*D7 | H7: =G7*land | I7: =CHOOSE(scen,Supuestos!B48,Supuestos!C48,Supuestos!D48) | J7: =H7*I7 | K7: =CHOOSE(scen,rep1,rep2,rep3)*J5 | L7: =H7*CHOOSE(scen,lead1,lead2,lead3)*CHOOSE(scen,lcv1,lcv2,lcv3) | M7: =J7+K7+L7 | N7: =M7*nose_per | O7: =M7*spot_per | P7: =IF(Y6-N7<60,MAX(125,CEILING(N7*2.5/125,1)*125),0) | Q7: =IF(AA6-O7<20,MAX(60,CEILING(O7*2.5*1.5,1))/1.5,0) | R7: =P7*r_nose+Q7*r_spot | S7: =Y6+P7 | T7: =Z6+P7*r_nose | U7: =IF(S7>0,T7/S7,c_nose) | V7: =AA6+Q7 | W7: =AB6+Q7*r_spot | X7: =IF(V7>0,W7/V7,c_spot) | Y7: =S7-N7 | Z7: =T7-N7*U7 | AA7: =V7-O7 | AB7: =W7-O7*X7 | AC7: =M7*aov | AD7: =M7*net_avg | AE7: =AC7-AD7 | AF7: =N7*U7+O7*X7 | AG7: =M7*pay_avg | AH7: =M7*(ship+pack) | AI7: =AD7*ret | AJ7: =AD7-AF7-AG7-AH7-AI7 | AK7: =fixed | AL7: =AJ7-B7-AK7 | AM7: =IF(J7>0,B7/J7,0) | AN7: =IF(B7>0,J7*aov/B7,0) | AO7: =R7*iva+AH7*iva | AP7: =IF(AND(A7>0,MOD(A7,3)=0),SUM(AE4:AE6)-SUM(AO4:AO6),0) | AQ7: =IF((AM5>contrib_avg),0,IF(AL6<aport_lim,aport,0)) | AR7: =AR6+AQ7+AC7-AG7-B7-AK7-R7*(1+iva)-AH7*(1+iva)-AP7-AI7
A8: 6 | B8: =IF((AM5>contrib_avg),0,MIN(cap2,MAX(B7,reinv*AJ7+AQ8),MAX(0,AR7+AQ8))) | C8: =CHOOSE(scen,cpm1,cpm2,cpm3) | D8: =CHOOSE(scen,ctr1,ctr2,ctr3) | E8: =C8/1000/D8 | F8: =B8/C8*1000 | G8: =F8*D8 | H8: =G8*land | I8: =CHOOSE(scen,Supuestos!B49,Supuestos!C49,Supuestos!D49) | J8: =H8*I8 | K8: =CHOOSE(scen,rep1,rep2,rep3)*J6 | L8: =H8*CHOOSE(scen,lead1,lead2,lead3)*CHOOSE(scen,lcv1,lcv2,lcv3) | M8: =J8+K8+L8 | N8: =M8*nose_per | O8: =M8*spot_per | P8: =IF(Y7-N8<60,MAX(125,CEILING(N8*2.5/125,1)*125),0) | Q8: =IF(AA7-O8<20,MAX(60,CEILING(O8*2.5*1.5,1))/1.5,0) | R8: =P8*r_nose+Q8*r_spot | S8: =Y7+P8 | T8: =Z7+P8*r_nose | U8: =IF(S8>0,T8/S8,c_nose) | V8: =AA7+Q8 | W8: =AB7+Q8*r_spot | X8: =IF(V8>0,W8/V8,c_spot) | Y8: =S8-N8 | Z8: =T8-N8*U8 | AA8: =V8-O8 | AB8: =W8-O8*X8 | AC8: =M8*aov | AD8: =M8*net_avg | AE8: =AC8-AD8 | AF8: =N8*U8+O8*X8 | AG8: =M8*pay_avg | AH8: =M8*(ship+pack) | AI8: =AD8*ret | AJ8: =AD8-AF8-AG8-AH8-AI8 | AK8: =fixed | AL8: =AJ8-B8-AK8 | AM8: =IF(J8>0,B8/J8,0) | AN8: =IF(B8>0,J8*aov/B8,0) | AO8: =R8*iva+AH8*iva | AP8: =IF(AND(A8>0,MOD(A8,3)=0),SUM(AE5:AE7)-SUM(AO5:AO7),0) | AQ8: =IF((AM5>contrib_avg),0,IF(AL7<aport_lim,aport,0)) | AR8: =AR7+AQ8+AC8-AG8-B8-AK8-R8*(1+iva)-AH8*(1+iva)-AP8-AI8
A9: 7 | B9: =IF((AM5>contrib_avg),0,MIN(cap2,MAX(B8,reinv*AJ8+AQ9),MAX(0,AR8+AQ9))) | C9: =CHOOSE(scen,cpm1,cpm2,cpm3) | D9: =CHOOSE(scen,ctr1,ctr2,ctr3) | E9: =C9/1000/D9 | F9: =B9/C9*1000 | G9: =F9*D9 | H9: =G9*land | I9: =CHOOSE(scen,Supuestos!B50,Supuestos!C50,Supuestos!D50) | J9: =H9*I9 | K9: =CHOOSE(scen,rep1,rep2,rep3)*J7 | L9: =H9*CHOOSE(scen,lead1,lead2,lead3)*CHOOSE(scen,lcv1,lcv2,lcv3) | M9: =J9+K9+L9 | N9: =M9*nose_per | O9: =M9*spot_per | P9: =IF(Y8-N9<60,MAX(125,CEILING(N9*2.5/125,1)*125),0) | Q9: =IF(AA8-O9<20,MAX(60,CEILING(O9*2.5*1.5,1))/1.5,0) | R9: =P9*r_nose+Q9*r_spot | S9: =Y8+P9 | T9: =Z8+P9*r_nose | U9: =IF(S9>0,T9/S9,c_nose) | V9: =AA8+Q9 | W9: =AB8+Q9*r_spot | X9: =IF(V9>0,W9/V9,c_spot) | Y9: =S9-N9 | Z9: =T9-N9*U9 | AA9: =V9-O9 | AB9: =W9-O9*X9 | AC9: =M9*aov | AD9: =M9*net_avg | AE9: =AC9-AD9 | AF9: =N9*U9+O9*X9 | AG9: =M9*pay_avg | AH9: =M9*(ship+pack) | AI9: =AD9*ret | AJ9: =AD9-AF9-AG9-AH9-AI9 | AK9: =fixed | AL9: =AJ9-B9-AK9 | AM9: =IF(J9>0,B9/J9,0) | AN9: =IF(B9>0,J9*aov/B9,0) | AO9: =R9*iva+AH9*iva | AP9: =IF(AND(A9>0,MOD(A9,3)=0),SUM(AE6:AE8)-SUM(AO6:AO8),0) | AQ9: =IF((AM5>contrib_avg),0,IF(AL8<aport_lim,aport,0)) | AR9: =AR8+AQ9+AC9-AG9-B9-AK9-R9*(1+iva)-AH9*(1+iva)-AP9-AI9
A10: 8 | B10: =IF((AM5>contrib_avg),0,MIN(cap2,MAX(B9,reinv*AJ9+AQ10),MAX(0,AR9+AQ10))) | C10: =CHOOSE(scen,cpm1,cpm2,cpm3) | D10: =CHOOSE(scen,ctr1,ctr2,ctr3) | E10: =C10/1000/D10 | F10: =B10/C10*1000 | G10: =F10*D10 | H10: =G10*land | I10: =CHOOSE(scen,Supuestos!B51,Supuestos!C51,Supuestos!D51) | J10: =H10*I10 | K10: =CHOOSE(scen,rep1,rep2,rep3)*J8 | L10: =H10*CHOOSE(scen,lead1,lead2,lead3)*CHOOSE(scen,lcv1,lcv2,lcv3) | M10: =J10+K10+L10 | N10: =M10*nose_per | O10: =M10*spot_per | P10: =IF(Y9-N10<60,MAX(125,CEILING(N10*2.5/125,1)*125),0) | Q10: =IF(AA9-O10<20,MAX(60,CEILING(O10*2.5*1.5,1))/1.5,0) | R10: =P10*r_nose+Q10*r_spot | S10: =Y9+P10 | T10: =Z9+P10*r_nose | U10: =IF(S10>0,T10/S10,c_nose) | V10: =AA9+Q10 | W10: =AB9+Q10*r_spot | X10: =IF(V10>0,W10/V10,c_spot) | Y10: =S10-N10 | Z10: =T10-N10*U10 | AA10: =V10-O10 | AB10: =W10-O10*X10 | AC10: =M10*aov | AD10: =M10*net_avg | AE10: =AC10-AD10 | AF10: =N10*U10+O10*X10 | AG10: =M10*pay_avg | AH10: =M10*(ship+pack) | AI10: =AD10*ret | AJ10: =AD10-AF10-AG10-AH10-AI10 | AK10: =fixed | AL10: =AJ10-B10-AK10 | AM10: =IF(J10>0,B10/J10,0) | AN10: =IF(B10>0,J10*aov/B10,0) | AO10: =R10*iva+AH10*iva | AP10: =IF(AND(A10>0,MOD(A10,3)=0),SUM(AE7:AE9)-SUM(AO7:AO9),0) | AQ10: =IF((AM5>contrib_avg),0,IF(AL9<aport_lim,aport,0)) | AR10: =AR9+AQ10+AC10-AG10-B10-AK10-R10*(1+iva)-AH10*(1+iva)-AP10-AI10
A11: 9 | B11: =IF((AM5>contrib_avg),0,MIN(cap2,MAX(B10,reinv*AJ10+AQ11),MAX(0,AR10+AQ11))) | C11: =CHOOSE(scen,cpm1,cpm2,cpm3) | D11: =CHOOSE(scen,ctr1,ctr2,ctr3) | E11: =C11/1000/D11 | F11: =B11/C11*1000 | G11: =F11*D11 | H11: =G11*land | I11: =CHOOSE(scen,Supuestos!B52,Supuestos!C52,Supuestos!D52) | J11: =H11*I11 | K11: =CHOOSE(scen,rep1,rep2,rep3)*J9 | L11: =H11*CHOOSE(scen,lead1,lead2,lead3)*CHOOSE(scen,lcv1,lcv2,lcv3) | M11: =J11+K11+L11 | N11: =M11*nose_per | O11: =M11*spot_per | P11: =IF(Y10-N11<60,MAX(125,CEILING(N11*2.5/125,1)*125),0) | Q11: =IF(AA10-O11<20,MAX(60,CEILING(O11*2.5*1.5,1))/1.5,0) | R11: =P11*r_nose+Q11*r_spot | S11: =Y10+P11 | T11: =Z10+P11*r_nose | U11: =IF(S11>0,T11/S11,c_nose) | V11: =AA10+Q11 | W11: =AB10+Q11*r_spot | X11: =IF(V11>0,W11/V11,c_spot) | Y11: =S11-N11 | Z11: =T11-N11*U11 | AA11: =V11-O11 | AB11: =W11-O11*X11 | AC11: =M11*aov | AD11: =M11*net_avg | AE11: =AC11-AD11 | AF11: =N11*U11+O11*X11 | AG11: =M11*pay_avg | AH11: =M11*(ship+pack) | AI11: =AD11*ret | AJ11: =AD11-AF11-AG11-AH11-AI11 | AK11: =fixed | AL11: =AJ11-B11-AK11 | AM11: =IF(J11>0,B11/J11,0) | AN11: =IF(B11>0,J11*aov/B11,0) | AO11: =R11*iva+AH11*iva | AP11: =IF(AND(A11>0,MOD(A11,3)=0),SUM(AE8:AE10)-SUM(AO8:AO10),0) | AQ11: =IF((AM5>contrib_avg),0,IF(AL10<aport_lim,aport,0)) | AR11: =AR10+AQ11+AC11-AG11-B11-AK11-R11*(1+iva)-AH11*(1+iva)-AP11-AI11
A12: 10 | B12: =IF((AM5>contrib_avg),0,MIN(cap2,MAX(B11,reinv*AJ11+AQ12),MAX(0,AR11+AQ12))) | C12: =CHOOSE(scen,cpm1,cpm2,cpm3) | D12: =CHOOSE(scen,ctr1,ctr2,ctr3) | E12: =C12/1000/D12 | F12: =B12/C12*1000 | G12: =F12*D12 | H12: =G12*land | I12: =CHOOSE(scen,Supuestos!B53,Supuestos!C53,Supuestos!D53) | J12: =H12*I12 | K12: =CHOOSE(scen,rep1,rep2,rep3)*J10 | L12: =H12*CHOOSE(scen,lead1,lead2,lead3)*CHOOSE(scen,lcv1,lcv2,lcv3) | M12: =J12+K12+L12 | N12: =M12*nose_per | O12: =M12*spot_per | P12: =IF(Y11-N12<60,MAX(125,CEILING(N12*2.5/125,1)*125),0) | Q12: =IF(AA11-O12<20,MAX(60,CEILING(O12*2.5*1.5,1))/1.5,0) | R12: =P12*r_nose+Q12*r_spot | S12: =Y11+P12 | T12: =Z11+P12*r_nose | U12: =IF(S12>0,T12/S12,c_nose) | V12: =AA11+Q12 | W12: =AB11+Q12*r_spot | X12: =IF(V12>0,W12/V12,c_spot) | Y12: =S12-N12 | Z12: =T12-N12*U12 | AA12: =V12-O12 | AB12: =W12-O12*X12 | AC12: =M12*aov | AD12: =M12*net_avg | AE12: =AC12-AD12 | AF12: =N12*U12+O12*X12 | AG12: =M12*pay_avg | AH12: =M12*(ship+pack) | AI12: =AD12*ret | AJ12: =AD12-AF12-AG12-AH12-AI12 | AK12: =fixed | AL12: =AJ12-B12-AK12 | AM12: =IF(J12>0,B12/J12,0) | AN12: =IF(B12>0,J12*aov/B12,0) | AO12: =R12*iva+AH12*iva | AP12: =IF(AND(A12>0,MOD(A12,3)=0),SUM(AE9:AE11)-SUM(AO9:AO11),0) | AQ12: =IF((AM5>contrib_avg),0,IF(AL11<aport_lim,aport,0)) | AR12: =AR11+AQ12+AC12-AG12-B12-AK12-R12*(1+iva)-AH12*(1+iva)-AP12-AI12
A13: 11 | B13: =IF((AM5>contrib_avg),0,MIN(cap2,MAX(B12,reinv*AJ12+AQ13),MAX(0,AR12+AQ13))) | C13: =CHOOSE(scen,cpm1,cpm2,cpm3) | D13: =CHOOSE(scen,ctr1,ctr2,ctr3) | E13: =C13/1000/D13 | F13: =B13/C13*1000 | G13: =F13*D13 | H13: =G13*land | I13: =CHOOSE(scen,Supuestos!B54,Supuestos!C54,Supuestos!D54) | J13: =H13*I13 | K13: =CHOOSE(scen,rep1,rep2,rep3)*J11 | L13: =H13*CHOOSE(scen,lead1,lead2,lead3)*CHOOSE(scen,lcv1,lcv2,lcv3) | M13: =J13+K13+L13 | N13: =M13*nose_per | O13: =M13*spot_per | P13: =IF(Y12-N13<60,MAX(125,CEILING(N13*2.5/125,1)*125),0) | Q13: =IF(AA12-O13<20,MAX(60,CEILING(O13*2.5*1.5,1))/1.5,0) | R13: =P13*r_nose+Q13*r_spot | S13: =Y12+P13 | T13: =Z12+P13*r_nose | U13: =IF(S13>0,T13/S13,c_nose) | V13: =AA12+Q13 | W13: =AB12+Q13*r_spot | X13: =IF(V13>0,W13/V13,c_spot) | Y13: =S13-N13 | Z13: =T13-N13*U13 | AA13: =V13-O13 | AB13: =W13-O13*X13 | AC13: =M13*aov | AD13: =M13*net_avg | AE13: =AC13-AD13 | AF13: =N13*U13+O13*X13 | AG13: =M13*pay_avg | AH13: =M13*(ship+pack) | AI13: =AD13*ret | AJ13: =AD13-AF13-AG13-AH13-AI13 | AK13: =fixed | AL13: =AJ13-B13-AK13 | AM13: =IF(J13>0,B13/J13,0) | AN13: =IF(B13>0,J13*aov/B13,0) | AO13: =R13*iva+AH13*iva | AP13: =IF(AND(A13>0,MOD(A13,3)=0),SUM(AE10:AE12)-SUM(AO10:AO12),0) | AQ13: =IF((AM5>contrib_avg),0,IF(AL12<aport_lim,aport,0)) | AR13: =AR12+AQ13+AC13-AG13-B13-AK13-R13*(1+iva)-AH13*(1+iva)-AP13-AI13
A14: 12 | B14: =IF((AM5>contrib_avg),0,MIN(cap2,MAX(B13,reinv*AJ13+AQ14),MAX(0,AR13+AQ14))) | C14: =CHOOSE(scen,cpm1,cpm2,cpm3) | D14: =CHOOSE(scen,ctr1,ctr2,ctr3) | E14: =C14/1000/D14 | F14: =B14/C14*1000 | G14: =F14*D14 | H14: =G14*land | I14: =CHOOSE(scen,Supuestos!B55,Supuestos!C55,Supuestos!D55) | J14: =H14*I14 | K14: =CHOOSE(scen,rep1,rep2,rep3)*J12 | L14: =H14*CHOOSE(scen,lead1,lead2,lead3)*CHOOSE(scen,lcv1,lcv2,lcv3) | M14: =J14+K14+L14 | N14: =M14*nose_per | O14: =M14*spot_per | P14: =IF(Y13-N14<60,MAX(125,CEILING(N14*2.5/125,1)*125),0) | Q14: =IF(AA13-O14<20,MAX(60,CEILING(O14*2.5*1.5,1))/1.5,0) | R14: =P14*r_nose+Q14*r_spot | S14: =Y13+P14 | T14: =Z13+P14*r_nose | U14: =IF(S14>0,T14/S14,c_nose) | V14: =AA13+Q14 | W14: =AB13+Q14*r_spot | X14: =IF(V14>0,W14/V14,c_spot) | Y14: =S14-N14 | Z14: =T14-N14*U14 | AA14: =V14-O14 | AB14: =W14-O14*X14 | AC14: =M14*aov | AD14: =M14*net_avg | AE14: =AC14-AD14 | AF14: =N14*U14+O14*X14 | AG14: =M14*pay_avg | AH14: =M14*(ship+pack) | AI14: =AD14*ret | AJ14: =AD14-AF14-AG14-AH14-AI14 | AK14: =fixed | AL14: =AJ14-B14-AK14 | AM14: =IF(J14>0,B14/J14,0) | AN14: =IF(B14>0,J14*aov/B14,0) | AO14: =R14*iva+AH14*iva | AP14: =IF(AND(A14>0,MOD(A14,3)=0),SUM(AE11:AE13)-SUM(AO11:AO13),0) | AQ14: =IF((AM5>contrib_avg),0,IF(AL13<aport_lim,aport,0)) | AR14: =AR13+AQ14+AC14-AG14-B14-AK14-R14*(1+iva)-AH14*(1+iva)-AP14-AI14
